{
  "menu": [
    {
      "url": "/",
      "name": "Dashboard",
      "icon": "menu-icon tf-icons ti ti-smart-home",
      "slug": "dashboard"
    },
    {
      "url": "report",
      "icon": "menu-icon tf-icons ti ti-report-search",
      "name": "Báo cáo",
      "slug": "report"
    },
    {
      "url": "schedule",
      "name": "Lịch làm việc",
      "icon": "menu-icon tf-icons ti ti-calendar-event",
      "slug": "schedule"
    },
    {
      "url": "user",
      "name": "Tài khoản",
      "icon": "menu-icon tf-icons ti ti-users-group",
      "slug": "user"
    },
    {
      "url": "store",
      "name": "Cửa hàng",
      "icon": "menu-icon tf-icons ti ti-building-store",
      "slug": "store"
    }
  ]
}
